MANIFEST.in
README.md
setup.py
MasLib/__init__.py
MasLib/classification.py
MasLib/clustering.py
MasLib/correlation.py
MasLib/encoding.py
MasLib/loading.py
MasLib/regressions.py
MasLib/sql.py
MasLib/text_coding.py
Maslib.egg-info/PKG-INFO
Maslib.egg-info/SOURCES.txt
Maslib.egg-info/dependency_links.txt
Maslib.egg-info/requires.txt
Maslib.egg-info/top_level.txt
tests/test_clustering.py
tests/test_correlation.py
tests/test_encoding.py
tests/test_grid_search.py
tests/test_loading.py
tests/test_regression.py
tests/test_text_coding.py