Metadata-Version: 2.1
Name: Maslib
Version: 0.2.1
Summary: This is a library for optimizing code for python
Author: Alecsandr_C.V.V
Author-email: dxomko@gmail.com
Classifier: Programming Language :: Python :: 3
Classifier: License :: OSI Approved :: MIT License
Classifier: Operating System :: OS Independent
Requires-Python: >=3.6
Requires-Dist: numpy
Requires-Dist: pandas
Requires-Dist: phik
Requires-Dist: matplotlib
Requires-Dist: scikit-learn
Requires-Dist: catboost
Requires-Dist: joblib
Requires-Dist: wordcloud
Requires-Dist: xgboost
Requires-Dist: nltk
Requires-Dist: pyodbc
Requires-Dist: mysql-connector-python
Requires-Dist: pymongo
Requires-Dist: psycopg2-binary
Requires-Dist: PyYAML
Requires-Dist: fastavro
Requires-Dist: pyorc
Requires-Dist: pdfplumber
